streamlit_app/2_🕵️‍♀️_POC_Overview.py
streamlit_app/3_✏️_POC_Overrides.py
streamlit_app/4_🚢_Onboard_POC.py
streamlit_app/__init__.py
streamlit_app/alarms_utils.py
streamlit_app/creds.py
streamlit_app/main.py
streamlit_app/env/bin/jp.py
streamlit_test/__init__.py
streamlit_test/globals.py
amzn_project_streamlit_app-1.0.dist-info/METADATA
amzn_project_streamlit_app-1.0.dist-info/WHEEL
amzn_project_streamlit_app-1.0.dist-info/top_level.txt
amzn_project_streamlit_app-1.0.dist-info/RECORD
